jkPyUtils/__init__.py
jkPyUtils/__version__.py
jkPyUtils/fetch.py
jkPyUtils/icache.py
jkPyUtils/requests2/__init__.py
jkPyUtils/requests2/fetch.py
jkPyUtils-0.0.3.dist-info/LICENSE
jkPyUtils-0.0.3.dist-info/METADATA
jkPyUtils-0.0.3.dist-info/WHEEL
jkPyUtils-0.0.3.dist-info/top_level.txt
jkPyUtils-0.0.3.dist-info/RECORD
