Metadata-Version: 2.1
Name: jkPyUtils
Version: 0.0.3
Summary: Common Utils for Python from Jackon
Home-page: https://github.com/JackonYang/jkPyUtils
Author: Jackon Yang
Author-email: i@jackon.me
License: MIT
Platform: UNKNOWN
Requires-Dist: requests (==2.25.1)
